friendly_arguments/__init__.py
friendly_arguments/named.py
friendly_arguments-0.2.0.dist-info/licenses/LICENSE.md
tests/__init__.py
tests/test_named.py
friendly_arguments-0.2.0.dist-info/METADATA
friendly_arguments-0.2.0.dist-info/WHEEL
friendly_arguments-0.2.0.dist-info/top_level.txt
friendly_arguments-0.2.0.dist-info/RECORD
