Metadata-Version: 2.4
Name: friendly-arguments
Version: 0.2.0
Summary: Easy way to use named arguments by means of python dictionaries
Home-page: https://github.com/Horlando-Leao/FriendlyArguments
Author: Horlando Leão
Author-email: horlandojcleao.developer@gmail.com
License: MIT
Keywords: dev,scripts,args,tools
Classifier: Intended Audience :: Developers
Classifier: License :: OSI Approved :: MIT License
Classifier: Natural Language :: English
Classifier: Programming Language :: Python :: 3
License-File: LICENSE.md
Dynamic: author
Dynamic: author-email
Dynamic: classifier
Dynamic: description
Dynamic: description-content-type
Dynamic: home-page
Dynamic: keywords
Dynamic: license
Dynamic: license-file
Dynamic: summary
